{
  "predictions": [
    {
      "region": "Region_34",
      "predicted_water_stress": 0.8221842339987464,
      "risk_level": "Very High"
    },
    {
      "region": "Region_11",
      "predicted_water_stress": 0.7957301934636494,
      "risk_level": "Very High"
    },
    {
      "region": "Region_33",
      "predicted_water_stress": 0.79009245048158,
      "risk_level": "Very High"
    },
    {
      "region": "Region_39",
      "predicted_water_stress": 0.7872756999420591,
      "risk_level": "Very High"
    },
    {
      "region": "Region_1",
      "predicted_water_stress": 0.7780357053798137,
      "risk_level": "Very High"
    },
    {
      "region": "Region_43",
      "predicted_water_stress": 0.7627376131916532,
      "risk_level": "Very High"
    },
    {
      "region": "Region_35",
      "predicted_water_stress": 0.7578241398960563,
      "risk_level": "Very High"
    },
    {
      "region": "Region_12",
      "predicted_water_stress": 0.744429667694976,
      "risk_level": "Very High"
    },
    {
      "region": "Region_7",
      "predicted_water_stress": 0.730405079833136,
      "risk_level": "Very High"
    },
    {
      "region": "Region_38",
      "predicted_water_stress": 0.6738638416984422,
      "risk_level": "High"
    }
  ],
  "insights": {
    "key_findings": [
      "Identified 9 regions experiencing critical water stress levels",
      "AI models predict 15-30% potential water savings through efficiency technologies",
      "Agriculture accounts for the largest share of water consumption in high-stress regions",
      "Climate change impact is accelerating stress in identified regions"
    ],
    "regional_hotspots": [
      "Region_34",
      "Region_11",
      "Region_33",
      "Region_39",
      "Region_1"
    ],
    "model_performance": {
      "random_forest": {
        "score": -1.1463764668312577
      },
      "gradient_boosting": {
        "score": -1.6081788019301824
      },
      "ensemble": {
        "score": -1.37727763438072
      }
    }
  },
  "recommendations": [
    {
      "region": "Northern Cape, South Africa",
      "priority": "Critical",
      "technologies": [
        "Drip irrigation systems (40-60% water savings)",
        "Soil moisture sensors for precision irrigation"
      ],
      "expected_impact": "Reduce agricultural water use by 30-50%",
      "implementation_cost": "Medium-High",
      "payback_period": "2-4 years"
    },
    {
      "region": "Sahel Region, Mali",
      "priority": "Critical",
      "technologies": [
        "Drip irrigation systems (40-60% water savings)",
        "Water harvesting and storage systems"
      ],
      "expected_impact": "Reduce agricultural water use by 30-50%",
      "implementation_cost": "Medium-High",
      "payback_period": "2-4 years"
    }
  ],
  "model_performance": {
    "random_forest": {
      "score": -1.1463764668312577
    },
    "gradient_boosting": {
      "score": -1.6081788019301824
    },
    "ensemble": {
      "score": -1.37727763438072
    }
  }
}